Mark2PY/Errors.py
Mark2PY/MD.py
Mark2PY/MU.py
Mark2PY/__init__.py
Mark2PY-0.5.3.dist-info/LICENSE
Mark2PY-0.5.3.dist-info/METADATA
Mark2PY-0.5.3.dist-info/WHEEL
Mark2PY-0.5.3.dist-info/top_level.txt
Mark2PY-0.5.3.dist-info/RECORD
