Metadata-Version: 2.1
Name: Mark2PY
Version: 0.5.3
Summary: this package help developers to write Markdown & Markup in python
Home-page: https://github.com/amjoshaghani/Mark2PY
Author: AMJoshaghani
Author-email: amjoshaghani@gmail.com
License: MIT
Platform: UNKNOWN
Classifier: Programming Language :: Python :: 3
Classifier: License :: OSI Approved :: MIT License
Classifier: Operating System :: OS Independent
